{"type": "Feature", "id": 12523233, "properties": {"woe:id": 12523233, "woe:parent_id": 1064105, "woe:name": "Nausori International Airport", "woe:placetype": 14, "woe:placetype_name": "Airport", "woe:lang": "ENG", "iso:country": "FJ", "meta:provider": ["geoplanet:7.3.1", "geoplanet:7.3.2", "geoplanet:7.4.0", "geoplanet:7.4.1", "geoplanet:7.5.1", "geoplanet:7.5.2", "geoplanet:7.6.0", "geoplanet:7.8.1", "geoplanet:7.9.0", "geoplanet:7.10.0", "geoplanet:8.0.0", "woeplanet:8.0.0"], "meta:indexed": "2020-08-20T20:21:19.268086", "woe:alias_ENG_V": ["SUV Airport", "SUV", "Nausori Airport", "Nausori International"], "meta:updated": "2020-08-22T02:58:57.247299", "woe:hierarchy": {"continent": 24865674, "country": 23424813, "town": 0, "planet": 1, "county": 0, "suburb": 0, "state": 2345335, "region": 0, "localadmin": 0}, "woe:timezone_id": 28350943, "woe:hash": "ruycr6h70uk9", "woe:centroid": [178.566666, -18.049999], "geom:latitude": -18.049999, "geom:longitude": 178.566666, "geom:hash": "ruycr6h70uk9", "woe:latitude": -18.049999, "geom:centroid": [178.566666, -18.049999], "woe:longitude": 178.566666, "woe:repo": "woeplanet-airport-fj"}, "geometry": {"coordinates": [178.566666, -18.049999], "type": "Point"}}